rlim/__init__.py
rlim/bundle.py
rlim/errors.py
rlim/ratelimiter.py
rlim/utils.py
rlim-1.0.0.dist-info/LICENSE
rlim-1.0.0.dist-info/METADATA
rlim-1.0.0.dist-info/WHEEL
rlim-1.0.0.dist-info/top_level.txt
rlim-1.0.0.dist-info/RECORD
