Metadata-Version: 2.1
Name: rlim
Version: 1.0.0
Summary: A modern Python rate limiting package
Author-email: "Tanner B. Corcoran" <tannerbcorcoran@gmail.com>
License: Copyright 2023 Tanner B. Corcoran
Project-URL: repository, https://github.com/tanrbobanr/rlim
Project-URL: documentation, https://github.com/tanrbobanr/rlim/blob/main/README.md
Project-URL: changelog, https://github.com/tanrbobanr/rlim/blob/main/changelog.md
Keywords: ratelimiter,ratelimit,rate limiting,rate limiter,api,decorator,context manager
Classifier: Development Status :: 5 - Production/Stable
Classifier: Intended Audience :: Developers
Classifier: License :: OSI Approved :: Apache Software License
Classifier: Operating System :: OS Independent
Classifier: Programming Language :: Python :: 3.8
Classifier: Programming Language :: Python :: 3.9
Classifier: Programming Language :: Python :: 3.10
Classifier: Programming Language :: Python :: 3.11
Classifier: Programming Language :: Python :: 3.12
Classifier: Programming Language :: Python :: 3
Classifier: Topic :: Software Development :: Libraries
Classifier: Topic :: Utilities
Classifier: Typing :: Typed
Requires-Python: >=3.8
License-File: LICENSE
